{
    "productId": "339",
    "title": "base de cama",
    "boldTitle": "calm",
    "selectedLink": "bases y sommiers",
    "dreamDelivery": true,
    "skus": "B80;B100;B140;B160;B180;B200",
    "isSquare": false,
    "layoutImages": [
        "https://calmessimple.com.ar/wp-content/uploads/2022/07/imgbase_1.webp",
        "https://calmessimple.com.ar/wp-content/uploads/2022/07/imgbase_4.webp",
        "https://calmessimple.com.ar/wp-content/uploads/2022/07/imgbase_2.webp",
        "https://calmessimple.com.ar/wp-content/uploads/2022/07/imgbase_3.webp"
    ],
    "layoutImagesHaveVideo": false,
    "accordionSpecsTexts": [
        {
            "nro": 1,
            "title":"30 noches de prueba",
            "answer":"<p>Prob치 cualquier producto de calm por <b>30 noches.</b> Si no te gusta, lo devolves y te reembolsamos <b>cada centavo.</b> As칤 de <b>simple como lo lees.</b></p>"
        },
        {
            "nro": 2,
            "title":"Env칤o gratis",
            "answer":"<p>Hacemos env칤o gratis a <b>todo el pa칤s.</b> Una vez que hagas la compra vamos a estar actualiz치ndote paso a paso del estado de tu pedido por correo electr칩nico.</p>"
        },
        {
            "nro": 3,
            "title":"12 cuotas sin inter칠s",
            "answer":"<p>Pod칠s pagar en <b>12 cuotas sin inter칠s</b> con todas las tarjetas que participan del programa <b>AHORA 12.</b></p>"
        }
    ],
    "specsSectionTitles": [
        {"title": "dimensiones de la ", "bold": "base para tu colch칩n"}
    ],
    "specsTexts": [
        {
            "title":"F치cil de armar",
            "subtitle":"<br/><br/>Pusimos especial foco en este punto y estamos orgullosos de <b>lo f치cil que es.</b> En tan solo <b>15 minutos</b> tenes lista tu nueva base! Olvidate de sufrir en las mudanzas, esta base es <b>muy simple de trasladar.</b>"
        },
        {
            "title":"Va muy bien con tu colch칩n",
            "subtitle":"<br/><br/>El apoyo en los listones de madera de eucalipto y el espacio optimo entre cada uno, hace que <b>la vida 칰til</b> de tu colch칩n sea mayor, as칤 como tambi칠n permite el paso de aire para que duermas <b>siempre fresco.</b>"
        },
        {
            "title":"Guardado inteligente",
            "subtitle":"<br/><br/>Nuestra base tiene 35cm de alto, siendo un muy buen lugar para aprovechar en los departamentos poco espaciosos, as칤 como tambi칠n por algunos amigos 游냤 游냠"
        }
    ],
    "specsImages": "https://calmessimple.com.ar/wp-content/uploads/2019/10/base-1-pata.webp",
    "specsValues": [
        { "name": "1 Plaza", "size": "80 x 190 cm" },
        { "name": "Plaza y 1/2", "size": "100 x 190 cm" },
        { "name": "2 Plazas", "size": "140 x 190 cm" },
        { "name": "Queen", "size": "160 x 200 cm" },
        { "name": "King", "size": "180 x 200 cm" },
        { "name": "Superking", "size": "200 x 200 cm" }
    ],
    "hasUnboxingSection": false,
    "hasTutorialSection": {
        "show": true,
        "title": "llega en caja y ",
        "boldTitle": "se arma as칤 de f치cil",
        "videoId": "nDQv4PXpOA0"
    },
    "faqAccordionTitle": {"title": "preguntas ", "bold": "frecuentes"},
    "faqAccordion":  [
        {
            "nro": 1,
            "title":"쯉on reales las 30 noches de prueba?",
            "answer":"<p>Te ofrecemos 30 noches de pruebas reales en tu casa. Creemos que para enamorarte de tu nueva cama necesitas pasar tiempo con ella. En el caso que no te guste te devolvemos el 100% de tu dinero.</p>"
        },
        {
            "nro": 2,
            "title":"쯈u칠 garant칤a tiene la base?",
            "answer":"<p>Damos 5 a침os de garant칤a. Esta sirve para cubrir a los clientes frente a defectos de f치brica, no de mal uso.</p>"
        },
        {
            "nro": 3,
            "title":"쮺u치ndo voy a recibir mi base?",
            "answer":"<p>Una vez que hagas la compra vamos a estar actualiz치ndote paso a paso del estado de tu pedido por correo electr칩nico. Adem치s podes hacer el seguimiento con tu mail y n칰mero de pedido en <a href='https://calmessimple.com.ar/seguimiento'> este link.<a></p>"
        },
        {
            "nro": 4,
            "title":"쮺u치nto peso soporta?",
            "answer":"<p>Soporta hasta 150kg por lado.</p>"
        },
        {
            "nro": 5,
            "title":"쮺칩mo se arma?",
            "answer":"<p>La base es muy f치cil de armar, en menos de 15 minutos la ten칠s lista! <a href='https://drive.google.com/file/d/1W2bWCzFbxhRZ1y8GQmhnrNw2CzACEOgI/view?usp=sharing'>Ac치</a> te dejamos el instructivo para que lo compruebes con tus propios ojos.</p>"
        }
    ],
    "specsAccordionTitle": {"title": "especificaciones ", "bold": "de la base"},
    "specsAccordion":  [
        {
            "nro": 1,
            "title":"Materiales",
            "answer":"<p>Utilizamos los mejores materiales: hierro soldado y madera de eucalipto.</p>"
        },
        {
            "nro": 2,
            "title":"Tama침o y peso",
            "answer":"<p><b>1 Plaza</b><br/>Dimensiones del colch칩n: 190cm x 80cm x 35cm.<br/>Tama침o de la caja: 18cm x 38cm x 198cm.<br/>Peso del env칤o: 24kg.<br/><br/><b>Plaza y 1/2</b><br/>Dimensiones del colch칩n: 190cm x 100cm x 35cm.<br/>Tama침o de la caja: 18cm x 38cm x 198cm.<br/>Peso del env칤o: 26kg.<br/><br/><b>2 Plazas</b><br/>Dimensiones del colch칩n: 190cm x 140cm x 35cm.<br/>Tama침o de la caja: 18cm x 38cm x 198cm.<br/>Peso del env칤o: 32kg.<br/><br/><b>Queen</b><br/>Dimensiones del colch칩n: 200cm x 160cm x 35cm.<br/>Tama침o de la caja: 18cm x 38cm x 198cm.<br/>Peso del env칤o: 37kg.<br/><br/><b>King</b><br/>Dimensiones del colch칩n: 200cm x 180cm x 35cm.<br/>Tama침o de la caja: 18cm x 38cm x 198cm.<br/>Peso del env칤o: 40kg.<br/><br/><b>Superking</b><br/>Dimensiones del colch칩n: 200cm x 200cm x 35cm.<br/>Tama침o de la caja: 18cm x 38cm x 198cm.<br/>Peso del env칤o: 42kg.</p>"
        },
        {
            "nro": 3,
            "title":"Pa칤s de fabricaci칩n",
            "answer":"<p>Orgullosamente hecha 100% en argentina</p>"
        }
    ]
}